odoo/addons/procurement_purchase_sale_no_grouping/README.rst
odoo/addons/procurement_purchase_sale_no_grouping/__init__.py
odoo/addons/procurement_purchase_sale_no_grouping/__manifest__.py
odoo/addons/procurement_purchase_sale_no_grouping/i18n/it.po
odoo/addons/procurement_purchase_sale_no_grouping/i18n/procurement_purchase_sale_no_grouping.pot
odoo/addons/procurement_purchase_sale_no_grouping/models/__init__.py
odoo/addons/procurement_purchase_sale_no_grouping/models/purchase_order.py
odoo/addons/procurement_purchase_sale_no_grouping/models/sale_order.py
odoo/addons/procurement_purchase_sale_no_grouping/readme/CONFIGURE.md
odoo/addons/procurement_purchase_sale_no_grouping/readme/CONTRIBUTORS.md
odoo/addons/procurement_purchase_sale_no_grouping/readme/DESCRIPTION.md
odoo/addons/procurement_purchase_sale_no_grouping/static/description/icon.png
odoo/addons/procurement_purchase_sale_no_grouping/static/description/index.html
odoo/addons/procurement_purchase_sale_no_grouping/tests/__init__.py
odoo/addons/procurement_purchase_sale_no_grouping/tests/test_procurement_purchase_no_grouping.py
odoo_addon_procurement_purchase_sale_no_grouping-17.0.1.0.0.4.dist-info/METADATA
odoo_addon_procurement_purchase_sale_no_grouping-17.0.1.0.0.4.dist-info/WHEEL
odoo_addon_procurement_purchase_sale_no_grouping-17.0.1.0.0.4.dist-info/top_level.txt
odoo_addon_procurement_purchase_sale_no_grouping-17.0.1.0.0.4.dist-info/RECORD
